{
			"id":7,
			"videoURL":"about_korea2_07",
			"sampleImages":"",	
			"word":"<h3><font color='#ea4156'><u>Vocabularies</u></font></h3>
    state religion &nbsp; 국교<br>
religion &nbsp; 종교<br>
religious &nbsp; 종교인<br>
decrease &nbsp; 감소하다<br>
Christianity &nbsp; 기독교<br>
Buddhism &nbsp; 불교<br>
both &nbsp; 둘다<br>
Buddha’s birthday &nbsp; 석가탄신일<br>
public holiday &nbsp; 공휴일
<br><br>
<h3><font color='#ea4156'><u>Tips</u></font></h3>

누군가 'Are you religious?' (종교인입니까?) 또는 'Do you have religion?' (종교를 가지고 있어요?)라고 물어 본다면 이렇게 대답 할 수 있어요. 
<br><br>
'I'm a Christian.' -> 나는 기독교 신자이다 <br>
'I'm a Buddhist.' -> 나는 불교 신자이다.<br>
'I'm a Catholic.' -> 나는 천주교 신자이다.<br>
'I’m a Muslim.' -> 나는 무슬림 신자이다.<br>
'I'm not religious.' -> 나는 무교이다.
    ",			
			"syncInfo":"0,0,3,6,12,17,24,28,30",	
			"content_subject":"Does Korea have a national religion?",
			"english_content_text": "Paul: Does Korea have a state religion?/<br>
Yuna: No, we have freedom of religion. /Less than half of South Koreans are religious and it’s decreasing every year though. /Christianity is the biggest and Buddhism is the second biggest. /The interesting thing is both Christmas and Buddha’s birthday are public holidays in Korea./<br>
Paul: What about you? Are you religious?/<br>
Yuna: I’m not, but I believe in God.",
			"korean_content_text": "Paul: 한국은 국교가 있나요?/<br><br>
Yuna: 아니오. 우리는 종교의 자유가 있어요./ 한국인의 반 미만이 종교를 가지고 있고 매년 감소하고 있어요. /기독교인이 가장 많고 다음으로는 불교신자가 많아요. /흥미로운 점은 한국에서는 크리스마스와 부처님 오신 날 둘 다 공휴일이라는 것이죠./<br>
Paul: 당신은 어때요? 종교가 있어요? /<br>
Yuna: 아니오, 하지만 신은 믿어요."
}